fastzdp_req/__init__.py
fastzdp_req-0.1.1.dist-info/LICENSE
fastzdp_req-0.1.1.dist-info/METADATA
fastzdp_req-0.1.1.dist-info/WHEEL
fastzdp_req-0.1.1.dist-info/RECORD
